{
  "latitude": 36.158024,
  "longitude": -86.76494,
  "generationtime_ms": 1041.568636894226,
  "utc_offset_seconds": -18000,
  "timezone": "America/Chicago",
  "timezone_abbreviation": "GMT-5",
  "elevation": 145.0,
  "daily_units": {
    "time": "iso8601",
    "sunshine_duration": "s",
    "uv_index_max": "",
    "shortwave_radiation_sum": "MJ/m\u00b2"
  },
  "daily": {
    "time": [
      "2026-06-08",
      "2026-06-09",
      "2026-06-10",
      "2026-06-11",
      "2026-06-12",
      "2026-06-13",
      "2026-06-14"
    ],
    "sunshine_duration": [
      7200.0,
      198.42,
      50560.25,
      44000.01,
      49205.2,
      48010.65,
      50917.76
    ],
    "uv_index_max": [
      5.3,
      7.9,
      8.1,
      8.05,
      8.1,
      7.55,
      7.55
    ],
    "shortwave_radiation_sum": [
      11.25,
      14.43,
      28.49,
      27.4,
      26.3,
      24.72,
      27.52
    ]
  }
}